[
  {
    "word": "TALES",
    "avg": 8697.42
  },
  {
    "word": "DARES",
    "avg": 8691.308
  },
  {
    "word": "ARILS",
    "avg": 8662.172
  },
  {
    "word": "MACES",
    "avg": 8635.704
  },
  {
    "word": "TABES",
    "avg": 8627.872
  },
  {
    "word": "CARLS",
    "avg": 8617.484
  },
  {
    "word": "GAPES",
    "avg": 8612.248
  },
  {
    "word": "TAXES",
    "avg": 8590.692
  },
  {
    "word": "HALER",
    "avg": 8585.2
  },
  {
    "word": "ASPER",
    "avg": 8584.948
  },
  {
    "word": "PIERS",
    "avg": 8584.604
  },
  {
    "word": "LAXES",
    "avg": 8583.496
  },
  {
    "word": "POSER",
    "avg": 8576.116
  },
  {
    "word": "LEASH",
    "avg": 8574.136
  },
  {
    "word": "ORCAS",
    "avg": 8570.04
  },
  {
    "word": "STOPE",
    "avg": 8564.468
  },
  {
    "word": "PITAS",
    "avg": 8554.34
  },
  {
    "word": "SINCE",
    "avg": 8543.856
  },
  {
    "word": "MALTS",
    "avg": 8533.34
  },
  {
    "word": "POKES",
    "avg": 8523.616
  },
  {
    "word": "CAPOS",
    "avg": 8521.2
  },
  {
    "word": "DARBS",
    "avg": 8517.552
  },
  {
    "word": "LIMOS",
    "avg": 8504.352
  },
  {
    "word": "HIRES",
    "avg": 8503.264
  },
  {
    "word": "RISER",
    "avg": 8494.384
  },
  {
    "word": "POSED",
    "avg": 8493.956
  },
  {
    "word": "ZONES",
    "avg": 8493.148
  },
  {
    "word": "KNARS",
    "avg": 8492.904
  },
  {
    "word": "AGONS",
    "avg": 8490.924
  },
  {
    "word": "HELIO",
    "avg": 8483.924
  },
  {
    "word": "RADIO",
    "avg": 8482.552
  },
  {
    "word": "COMAS",
    "avg": 8476.608
  },
  {
    "word": "IZARS",
    "avg": 8475.192
  },
  {
    "word": "MICAS",
    "avg": 8474.392
  },
  {
    "word": "HEART",
    "avg": 8473.348
  },
  {
    "word": "DEADS",
    "avg": 8471.088
  },
  {
    "word": "TILED",
    "avg": 8464.408
  },
  {
    "word": "DURNS",
    "avg": 8462.528
  },
  {
    "word": "EPICS",
    "avg": 8459.712
  },
  {
    "word": "JONES",
    "avg": 8453.232
  },
  {
    "word": "LEFTS",
    "avg": 8450.8
  },
  {
    "word": "SKIED",
    "avg": 8450.8
  },
  {
    "word": "SPIRT",
    "avg": 8448.256
  },
  {
    "word": "GAYER",
    "avg": 8444.6
  },
  {
    "word": "PEATY",
    "avg": 8425.02
  },
  {
    "word": "BAGEL",
    "avg": 8423.82
  },
  {
    "word": "CAPED",
    "avg": 8423.264
  },
  {
    "word": "OLEOS",
    "avg": 8422.284
  },
  {
    "word": "HILTS",
    "avg": 8414.324
  },
  {
    "word": "WAULS",
    "avg": 8409.808
  },
  {
    "word": "PARRS",
    "avg": 8408.804
  },
  {
    "word": "BAHTS",
    "avg": 8402.256
  },
  {
    "word": "PRIDE",
    "avg": 8400.856
  },
  {
    "word": "VENTS",
    "avg": 8392.22
  },
  {
    "word": "MAVIS",
    "avg": 8390.108
  },
  {
    "word": "LAZED",
    "avg": 8389.124
  },
  {
    "word": "VELDS",
    "avg": 8382.344
  },
  {
    "word": "JAPER",
    "avg": 8378.88
  },
  {
    "word": "SOWAR",
    "avg": 8374.844
  },
  {
    "word": "CAROM",
    "avg": 8374.604
  },
  {
    "word": "PEASE",
    "avg": 8370.036
  },
  {
    "word": "WIVES",
    "avg": 8368.392
  },
  {
    "word": "LOATH",
    "avg": 8354.856
  },
  {
    "word": "TAPAS",
    "avg": 8344.06
  },
  {
    "word": "NOOSE",
    "avg": 8341.676
  },
  {
    "word": "CRASH",
    "avg": 8341.128
  },
  {
    "word": "LEGIT",
    "avg": 8339.136
  },
  {
    "word": "BREAK",
    "avg": 8337.856
  },
  {
    "word": "RYNDS",
    "avg": 8325.856
  },
  {
    "word": "RAYAS",
    "avg": 8324.012
  },
  {
    "word": "EXITS",
    "avg": 8320.44
  },
  {
    "word": "HAINT",
    "avg": 8320.396
  },
  {
    "word": "BIOME",
    "avg": 8318.672
  },
  {
    "word": "BUSED",
    "avg": 8317.712
  },
  {
    "word": "PILAU",
    "avg": 8307.92
  },
  {
    "word": "AURAE",
    "avg": 8307.416
  },
  {
    "word": "WROTE",
    "avg": 8307.108
  },
  {
    "word": "VOLTE",
    "avg": 8303.94
  },
  {
    "word": "BENES",
    "avg": 8303.845
  },
  {
    "word": "CANID",
    "avg": 8300.712
  },
  {
    "word": "TURKS",
    "avg": 8298.34
  },
  {
    "word": "PODIA",
    "avg": 8298.04
  },
  {
    "word": "ROWAN",
    "avg": 8291.312
  },
  {
    "word": "JOINS",
    "avg": 8285.392
  },
  {
    "word": "MINOR",
    "avg": 8284.34
  },
  {
    "word": "ILLER",
    "avg": 8283.12
  },
  {
    "word": "FAYED",
    "avg": 8272.492
  },
  {
    "word": "GRAVE",
    "avg": 8272.028
  },
  {
    "word": "BERTH",
    "avg": 8266.948
  },
  {
    "word": "WANKS",
    "avg": 8261.9
  },
  {
    "word": "AMITY",
    "avg": 8258.05
  },
  {
    "word": "MALLS",
    "avg": 8255.284
  },
  {
    "word": "MODAL",
    "avg": 8253.94
  },
  {
    "word": "DENSE",
    "avg": 8253
  },
  {
    "word": "FETES",
    "avg": 8252.82
  },
  {
    "word": "BRUIT",
    "avg": 8250.484
  },
  {
    "word": "TSUBA",
    "avg": 8239.7
  },
  {
    "word": "STOMP",
    "avg": 8239.31
  },
  {
    "word": "SLABS",
    "avg": 8238.392
  },
  {
    "word": "COBIA",
    "avg": 8237.664
  },
  {
    "word": "FUMER",
    "avg": 8230.58
  },
  {
    "word": "NICAD",
    "avg": 8230.244
  },
  {
    "word": "TALKY",
    "avg": 8220.14
  },
  {
    "word": "WYLES",
    "avg": 8213.632
  },
  {
    "word": "NARKY",
    "avg": 8188.625
  },
  {
    "word": "ALGAS",
    "avg": 8185.492
  },
  {
    "word": "PESKY",
    "avg": 8182.444
  },
  {
    "word": "CASKY",
    "avg": 8166.516
  },
  {
    "word": "GYVES",
    "avg": 8166.116
  },
  {
    "word": "TRAMP",
    "avg": 8153.748
  },
  {
    "word": "SMELL",
    "avg": 8141.16
  },
  {
    "word": "PUJAS",
    "avg": 8140.608
  },
  {
    "word": "DROPT",
    "avg": 8140.54
  },
  {
    "word": "LUMPS",
    "avg": 8134.06
  },
  {
    "word": "PRIER",
    "avg": 8131.584
  },
  {
    "word": "GAWSY",
    "avg": 8130.328
  },
  {
    "word": "NUKED",
    "avg": 8110.55
  },
  {
    "word": "DURRS",
    "avg": 8109.228
  },
  {
    "word": "FOEHN",
    "avg": 8108.664
  },
  {
    "word": "POSTS",
    "avg": 8095.948
  },
  {
    "word": "CHYLE",
    "avg": 8092.232
  },
  {
    "word": "PILIS",
    "avg": 8083.048
  },
  {
    "word": "CLOUT",
    "avg": 8081.856
  },
  {
    "word": "NOWAY",
    "avg": 8080.856
  },
  {
    "word": "PROSO",
    "avg": 8073.424
  },
  {
    "word": "SCULK",
    "avg": 8070.332
  },
  {
    "word": "PURSY",
    "avg": 8068.872
  },
  {
    "word": "AXION",
    "avg": 8064.164
  },
  {
    "word": "DEFOG",
    "avg": 8060.832
  },
  {
    "word": "WINKS",
    "avg": 8058.8
  },
  {
    "word": "BRACH",
    "avg": 8054.316
  },
  {
    "word": "HAULM",
    "avg": 8049.992
  },
  {
    "word": "JOUAL",
    "avg": 8032.112
  },
  {
    "word": "SPOON",
    "avg": 8027.588
  },
  {
    "word": "GRUNT",
    "avg": 8007.536
  },
  {
    "word": "BURIN",
    "avg": 8004.616
  },
  {
    "word": "GISTS",
    "avg": 8002.096
  },
  {
    "word": "JUICE",
    "avg": 7996.424
  },
  {
    "word": "SIGIL",
    "avg": 7994.204
  },
  {
    "word": "SALAL",
    "avg": 7991.892
  },
  {
    "word": "CARRY",
    "avg": 7985.096
  },
  {
    "word": "QUIPS",
    "avg": 7972.436
  },
  {
    "word": "SPITS",
    "avg": 7970.095
  },
  {
    "word": "TUMPS",
    "avg": 7968.58
  },
  {
    "word": "YOGIC",
    "avg": 7961.604
  },
  {
    "word": "OCTYL",
    "avg": 7941.236
  },
  {
    "word": "ETHER",
    "avg": 7924.184
  },
  {
    "word": "YAHOO",
    "avg": 7916.64
  },
  {
    "word": "FLANK",
    "avg": 7904.064
  },
  {
    "word": "BRUSK",
    "avg": 7902.108
  },
  {
    "word": "AGORA",
    "avg": 7882.076
  },
  {
    "word": "LINGY",
    "avg": 7880.872
  },
  {
    "word": "HIGHS",
    "avg": 7879.12
  },
  {
    "word": "LEECH",
    "avg": 7866.704
  },
  {
    "word": "GONIF",
    "avg": 7854.256
  },
  {
    "word": "KAVAS",
    "avg": 7840.52
  },
  {
    "word": "CHIRP",
    "avg": 7837.332
  },
  {
    "word": "MUTTS",
    "avg": 7830.864
  },
  {
    "word": "PRINK",
    "avg": 7828.956
  },
  {
    "word": "BAWDY",
    "avg": 7807.748
  },
  {
    "word": "FROWN",
    "avg": 7792.708
  },
  {
    "word": "BABAS",
    "avg": 7791.852
  },
  {
    "word": "COUTH",
    "avg": 7784.53
  },
  {
    "word": "ANYON",
    "avg": 7780.624
  },
  {
    "word": "ZOONS",
    "avg": 7778.536
  },
  {
    "word": "DODGE",
    "avg": 7775.972
  },
  {
    "word": "SLUFF",
    "avg": 7756.34
  },
  {
    "word": "HEIGH",
    "avg": 7741.12
  },
  {
    "word": "ATMAN",
    "avg": 7737.524
  },
  {
    "word": "CASAS",
    "avg": 7734.82
  },
  {
    "word": "BOVID",
    "avg": 7732.38
  },
  {
    "word": "DOWRY",
    "avg": 7724.456
  },
  {
    "word": "CHEVY",
    "avg": 7712.336
  },
  {
    "word": "SWILL",
    "avg": 7696.76
  },
  {
    "word": "SOGGY",
    "avg": 7678.96
  },
  {
    "word": "VISIT",
    "avg": 7669.336
  },
  {
    "word": "CLOOT",
    "avg": 7660.932
  },
  {
    "word": "CIVIE",
    "avg": 7590.54
  },
  {
    "word": "FILLO",
    "avg": 7589.736
  },
  {
    "word": "MAMAS",
    "avg": 7588.132
  },
  {
    "word": "KOPPA",
    "avg": 7586.12
  },
  {
    "word": "SWIGS",
    "avg": 7577.66
  },
  {
    "word": "WRUNG",
    "avg": 7567.528
  },
  {
    "word": "PAGAN",
    "avg": 7544.24
  },
  {
    "word": "HELVE",
    "avg": 7542.44
  },
  {
    "word": "MURKY",
    "avg": 7534.248
  },
  {
    "word": "CONDO",
    "avg": 7483.884
  },
  {
    "word": "FREER",
    "avg": 7448.364
  },
  {
    "word": "RIBBY",
    "avg": 7433.25
  },
  {
    "word": "ZILCH",
    "avg": 7427.368
  },
  {
    "word": "NAPPA",
    "avg": 7298.248
  },
  {
    "word": "BILLY",
    "avg": 7283.356
  },
  {
    "word": "BOOTY",
    "avg": 7247.424
  },
  {
    "word": "TUBBY",
    "avg": 6898.16
  },
  {
    "word": "PAPPY",
    "avg": 6760.236
  },
  {
    "word": "MAMBA",
    "avg": 6643.236
  },
  {
    "word": "BLUFF",
    "avg": 6448.565
  },
  {
    "word": "VUGGY",
    "avg": 6007.944
  }
]